fpga/dds.sv
// authors: George Davis and Matthew Molinar
// emails: gdavis@hmc.edu and mmolinar@hmc.edu
// date created: 11/11/2025

// dds.sv

/////////////////////////////////////////////
// Direct Digital Synthesis module -

// Outputs will be fed into an external DAC
// which will be used to generate analog
// waveforms
/////////////////////////////////////////////

module dds # (
    parameter int    DAC_WIDTH = 8,                 // Bit width for external DAC
    parameter int    PHASE_WIDTH = 32,              // Width phase accumulator
    parameter int    FULL_WAVE = 256,               // Size of full sine wave
    parameter        LUT_FILE = "dds_lut.txt"   // ROM for LUT
) (
    input logic                   clk,
    input logic                   reset,  // active low reset
    input logic [PHASE_WIDTH-1:0] phase_inc,
    output logic [DAC_WIDTH-1:0]  dac_out
);

// Phase Accumulator
logic [PHASE_WIDTH-1:0] phase_acc = 0;

always_ff @(posedge clk) begin
    if(~reset) begin
        phase_acc <= 0;
    end else begin
        phase_acc <= phase_acc + phase_inc;
    end
end

// Quarter-wave sine LUT
localparam int QUARTER_LUT = FULL_WAVE / 4;     // size of quarter-wave LUT
localparam int LUT_BITS = $clog2(QUARTER_LUT);  // bits needed for LUT adder

// Using the first 2 bits for tracking quadrant
logic [1:0] quadrant;
assign quadrant = phase_acc[PHASE_WIDTH-1 -: 2];

// Remaining bits are use to pick values from the LUT
logic [LUT_BITS-1:0] lut_addr_base;
assign lut_addr_base = phase_acc[PHASE_WIDTH-3 -: LUT_BITS];

// ROM block for LUT
(* rom_style = "block" *)
logic [DAC_WIDTH-1:0] rom [0:QUARTER_LUT-1];

// Read LUT
initial begin
    $readmemh(LUT_FILE, rom);
end

// Assign LUT position based on the current quadrant
logic [LUT_BITS-1:0] lut_addr;
always_comb begin
        // read the table backwards for quadrants 1 and 3
        if (quadrant == 2'b01 || quadrant == 2'b11) begin
            lut_addr = ~lut_addr_base;
        end else begin
            lut_addr = lut_addr_base;
        end
    end

// Read ROM
logic [DAC_WIDTH-1:0] lut_out;
always_ff @(posedge clk) begin
    lut_out <= rom[lut_addr];
end

// Reconstruct the full sine wave from the amplitude LUT
logic [DAC_WIDTH-1:0] dac_out_reg;
always_ff @(posedge clk) begin
    if (~reset) begin
        dac_out_reg <= 8'h7F; // Reset to the midpoint (127)
    end else begin
        // For quadrants 2 and 3, subtract amplitude from midpoint
        if (quadrant[1]) begin
            dac_out_reg <= 8'h7F - lut_out;
        // For quadrants 0 and 1, add amplitude to midpoint
        end else begin
            dac_out_reg <= 8'h7F + lut_out;
        end
    end
end

// Output Logic
assign dac_out = dac_out_reg;

endmodule

fpga/dds_tb.sv
// authors: George Davis and Matthew Molinar
// emails: gdavis@hmc.edu and mmolinar@hmc.edu
// date created: 11/11/2025

// dds_tb.sv

/////////////////////////////////////////////
// Direct Digital Synthesis testbench
/////////////////////////////////////////////

`timescale 1ns/1ps

module dds_tb;

    // Parameters
    localparam DAC_WIDTH   = 8;
    localparam PHASE_WIDTH = 32;
    localparam FULL_WAVE   = 256;
    localparam LUT_FILE    = "dds_lut.txt";
    
    // Signals
    logic                   clk;
    logic                   reset;
    logic [PHASE_WIDTH-1:0] phase_inc;
    logic [DAC_WIDTH-1:0]   dac_out;

    logic [31:0]            error_count;
    logic [DAC_WIDTH-1:0]   expected_val;


    // Instantiate DDS
    dds #(
        .DAC_WIDTH(DAC_WIDTH),
        .PHASE_WIDTH(PHASE_WIDTH),
        .FULL_WAVE(FULL_WAVE),
        .LUT_FILE(LUT_FILE)
    ) dut (
        .clk(clk),
        .reset(reset),
        .phase_inc(phase_inc),
        .dac_out(dac_out)
    );

    // Generate clock
    always begin
        clk = 1; #5;
        clk = 0; #5;
    end

    // Start of test
    initial begin

        //waveform dumping
        $dumpfile("dds.vcd");
        $dumpvars(0, dds_tb);

        // Initialize INputs
        clk = 0;
        reset = 0;
        phase_inc = '0;
        error_count = 0;
        expected_val = 0;


        #30;
        reset = 1;  // Active low reset
        #10;

        // Set phase_inc to produce one full sine wave over 256 clock cycles
        phase_inc = (1 << (PHASE_WIDTH - $clog2(FULL_WAVE)));
        #10;
        
        // checking outputs
        for (int i = 0; i < FULL_WAVE; i = i + 1) begin
            #10;
            
            // Check the value that was calculated in the previous cycle
            case (i)
                // At 0 degrees, sin(0) = 0 and output should be midpoint (128)
                0: begin
                    expected_val = 8'h7F;
                    if (dac_out !== expected_val) begin
                        $display("ERROR at 0 degrees (sample %0d): got %h, expected %h", i, dac_out, expected_val);
                        error_count++;
                    end
                end
                
                // At 90 degrees, sin(pi/2) = 1 and output should be the peak
                (FULL_WAVE/4): begin
                    expected_val = 8'hFE;
                    if (dac_out !== expected_val) begin
                        $display("ERROR at 90 degrees (sample %0d): got %h, expected %h", i, dac_out, expected_val);
                        error_count++;
                    end
                end

                // At 180 degrees, sin(pi) = 0 and output should be midpoint (128)
                (FULL_WAVE/2): begin
                    expected_val = 8'h7F;
                    if (dac_out !== expected_val) begin
                        $display("ERROR at 180 degrees (sample %0d): got %h, expected %h", i, dac_out, expected_val);
                        error_count++;
                    end
                end

                // At 270 degrees, sin(3pi/2) = -1 and output should be min value
                (3*FULL_WAVE/4): begin
                    expected_val = 8'h00;
                    if (dac_out !== expected_val) begin
                        $display("ERROR at 270 degrees (sample %0d): got %h, expected %h", i, dac_out, expected_val);
                        error_count++;
                    end
                end
            endcase
        end

        if (error_count == 0) begin
            $display("All key points passed");
        end else begin
            $display("%0d key points failed", error_count);
        end

        $display("Test completed");
        $finish;
    end

endmodule

fpga/dds.vcd
$date
	Thu Nov 13 20:26:29 2025
$end
$version
	Icarus Verilog
$end
$timescale
	1ps
$end
$scope module dds_tb $end
$var wire 8 ! dac_out [7:0] $end
$var parameter 32 " DAC_WIDTH $end
$var parameter 32 # FULL_WAVE $end
$var parameter 88 $ LUT_FILE $end
$var parameter 32 % PHASE_WIDTH $end
$var reg 1 & clk $end
$var reg 32 ' error_count [31:0] $end
$var reg 8 ( expected_val [7:0] $end
$var reg 32 ) phase_inc [31:0] $end
$var reg 1 * reset $end
$scope module dut $end
$var wire 1 & clk $end
$var wire 8 + dac_out [7:0] $end
$var wire 32 , phase_inc [31:0] $end
$var wire 1 * reset $end
$var wire 2 - quadrant [1:0] $end
$var wire 6 . lut_addr_base [5:0] $end
$var parameter 32 / DAC_WIDTH $end
$var parameter 32 0 FULL_WAVE $end
$var parameter 32 1 LUT_BITS $end
$var parameter 88 2 LUT_FILE $end
$var parameter 32 3 PHASE_WIDTH $end
$var parameter 32 4 QUARTER_LUT $end
$var reg 8 5 dac_out_reg [7:0] $end
$var reg 6 6 lut_addr [5:0] $end
$var reg 8 7 lut_out [7:0] $end
$var reg 32 8 phase_acc [31:0] $end
$upscope $end
$scope begin $ivl_for_loop0 $end
$var integer 32 9 i [31:0] $end
$upscope $end
$upscope $end
$enddefinitions $end
$comment Show the parameter values. $end
$dumpall
b1000000 4
b100000 3
b110010001100100011100110101111101101100011101010111010000101110011101000111100001110100 2
b110 1
b100000000 0
b1000 /
b100000 %
b110010001100100011100110101111101101100011101010111010000101110011101000111100001110100 $
b100000000 #
b1000 "
$end
#0
$dumpvars
b0 9
b0 8
bx 7
b0 6
b1111111 5
b0 .
b0 -
b0 ,
b1111111 +
0*
b0 )
b0 (
b0 '
0&
b1111111 !
$end
#10000
b0 7
1&
#15000
0&
#20000
1&
#25000
0&
#30000
1&
1*
#35000
0&
#40000
b1 6
b1 .
b1000000000000000000000000 8
1&
b1000000000000000000000000 )
b1000000000000000000000000 ,
#45000
0&
#50000
b10 6
b10 .
b11 7
b10000000000000000000000000 8
1&
#55000
0&
#60000
b11 6
b11 .
b11000000000000000000000000 8
b110 7
b10000010 !
b10000010 +
b10000010 5
1&
b1 9
b1111111 (
#65000
0&
#70000
b100 6
b100 .
b10000101 !
b10000101 +
b10000101 5
b1001 7
b100000000000000000000000000 8
1&
b10 9
#75000
0&
#80000
b101 6
b101 .
b101000000000000000000000000 8
b1100 7
b10001000 !
b10001000 +
b10001000 5
1&
b11 9
#85000
0&
#90000
b110 6
b110 .
b10001011 !
b10001011 +
b10001011 5
b10000 7
b110000000000000000000000000 8
1&
b100 9
#95000
0&
#100000
b111 6
b111 .
b111000000000000000000000000 8
b10011 7
b10001111 !
b10001111 +
b10001111 5
1&
b101 9
#105000
0&
#110000
b1000 6
b1000 .
b10010010 !
b10010010 +
b10010010 5
b10110 7
b1000000000000000000000000000 8
1&
b110 9
#115000
0&
#120000
b1001 6
b1001 .
b1001000000000000000000000000 8
b11001 7
b10010101 !
b10010101 +
b10010101 5
1&
b111 9
#125000
0&
#130000
b1010 6
b1010 .
b10011000 !
b10011000 +
b10011000 5
b11100 7
b1010000000000000000000000000 8
1&
b1000 9
#135000
0&
#140000
b1011 6
b1011 .
b1011000000000000000000000000 8
b11111 7
b10011011 !
b10011011 +
b10011011 5
1&
b1001 9
#145000
0&
#150000
b1100 6
b1100 .
b10011110 !
b10011110 +
b10011110 5
b100010 7
b1100000000000000000000000000 8
1&
b1010 9
#155000
0&
#160000
b1101 6
b1101 .
b1101000000000000000000000000 8
b100101 7
b10100001 !
b10100001 +
b10100001 5
1&
b1011 9
#165000
0&
#170000
b1110 6
b1110 .
b10100100 !
b10100100 +
b10100100 5
b101000 7
b1110000000000000000000000000 8
1&
b1100 9
#175000
0&
#180000
b1111 6
b1111 .
b1111000000000000000000000000 8
b101011 7
b10100111 !
b10100111 +
b10100111 5
1&
b1101 9
#185000
0&
#190000
b10000 6
b10000 .
b10101010 !
b10101010 +
b10101010 5
b101110 7
b10000000000000000000000000000 8
1&
b1110 9
#195000
0&
#200000
b10001 6
b10001 .
b10001000000000000000000000000 8
b110001 7
b10101101 !
b10101101 +
b10101101 5
1&
b1111 9
#205000
0&
#210000
b10010 6
b10010 .
b10110000 !
b10110000 +
b10110000 5
b110011 7
b10010000000000000000000000000 8
1&
b10000 9
#215000
0&
#220000
b10011 6
b10011 .
b10011000000000000000000000000 8
b110110 7
b10110010 !
b10110010 +
b10110010 5
1&
b10001 9
#225000
0&
#230000
b10100 6
b10100 .
b10110101 !
b10110101 +
b10110101 5
b111001 7
b10100000000000000000000000000 8
1&
b10010 9
#235000
0&
#240000
b10101 6
b10101 .
b10101000000000000000000000000 8
b111100 7
b10111000 !
b10111000 +
b10111000 5
1&
b10011 9
#245000
0&
#250000
b10110 6
b10110 .
b10111011 !
b10111011 +
b10111011 5
b111111 7
b10110000000000000000000000000 8
1&
b10100 9
#255000
0&
#260000
b10111 6
b10111 .
b10111000000000000000000000000 8
b1000001 7
b10111110 !
b10111110 +
b10111110 5
1&
b10101 9
#265000
0&
#270000
b11000 6
b11000 .
b11000000 !
b11000000 +
b11000000 5
b1000100 7
b11000000000000000000000000000 8
1&
b10110 9
#275000
0&
#280000
b11001 6
b11001 .
b11001000000000000000000000000 8
b1000111 7
b11000011 !
b11000011 +
b11000011 5
1&
b10111 9
#285000
0&
#290000
b11010 6
b11010 .
b11000110 !
b11000110 +
b11000110 5
b1001001 7
b11010000000000000000000000000 8
1&
b11000 9
#295000
0&
#300000
b11011 6
b11011 .
b11011000000000000000000000000 8
b1001100 7
b11001000 !
b11001000 +
b11001000 5
1&
b11001 9
#305000
0&
#310000
b11100 6
b11100 .
b11001011 !
b11001011 +
b11001011 5
b1001110 7
b11100000000000000000000000000 8
1&
b11010 9
#315000
0&
#320000
b11101 6
b11101 .
b11101000000000000000000000000 8
b1010001 7
b11001101 !
b11001101 +
b11001101 5
1&
b11011 9
#325000
0&
#330000
b11110 6
b11110 .
b11010000 !
b11010000 +
b11010000 5
b1010011 7
b11110000000000000000000000000 8
1&
b11100 9
#335000
0&
#340000
b11111 6
b11111 .
b11111000000000000000000000000 8
b1010101 7
b11010010 !
b11010010 +
b11010010 5
1&
b11101 9
#345000
0&
#350000
b100000 6
b100000 .
b11010100 !
b11010100 +
b11010100 5
b1011000 7
b100000000000000000000000000000 8
1&
b11110 9
#355000
0&
#360000
b100001 6
b100001 .
b100001000000000000000000000000 8
b1011010 7
b11010111 !
b11010111 +
b11010111 5
1&
b11111 9
#365000
0&
#370000
b100010 6
b100010 .
b11011001 !
b11011001 +
b11011001 5
b1011100 7
b100010000000000000000000000000 8
1&
b100000 9
#375000
0&
#380000
b100011 6
b100011 .
b100011000000000000000000000000 8
b1011110 7
b11011011 !
b11011011 +
b11011011 5
1&
b100001 9
#385000
0&
#390000
b100100 6
b100100 .
b11011101 !
b11011101 +
b11011101 5
b1100000 7
b100100000000000000000000000000 8
1&
b100010 9
#395000
0&
#400000
b100101 6
b100101 .
b100101000000000000000000000000 8
b1100010 7
b11011111 !
b11011111 +
b11011111 5
1&
b100011 9
#405000
0&
#410000
b100110 6
b100110 .
b11100001 !
b11100001 +
b11100001 5
b1100100 7
b100110000000000000000000000000 8
1&
b100100 9
#415000
0&
#420000
b100111 6
b100111 .
b100111000000000000000000000000 8
b1100110 7
b11100011 !
b11100011 +
b11100011 5
1&
b100101 9
#425000
0&
#430000
b101000 6
b101000 .
b11100101 !
b11100101 +
b11100101 5
b1101000 7
b101000000000000000000000000000 8
1&
b100110 9
#435000
0&
#440000
b101001 6
b101001 .
b101001000000000000000000000000 8
b1101010 7
b11100111 !
b11100111 +
b11100111 5
1&
b100111 9
#445000
0&
#450000
b101010 6
b101010 .
b11101001 !
b11101001 +
b11101001 5
b1101011 7
b101010000000000000000000000000 8
1&
b101000 9
#455000
0&
#460000
b101011 6
b101011 .
b101011000000000000000000000000 8
b1101101 7
b11101010 !
b11101010 +
b11101010 5
1&
b101001 9
#465000
0&
#470000
b101100 6
b101100 .
b11101100 !
b11101100 +
b11101100 5
b1101111 7
b101100000000000000000000000000 8
1&
b101010 9
#475000
0&
#480000
b101101 6
b101101 .
b101101000000000000000000000000 8
b1110000 7
b11101110 !
b11101110 +
b11101110 5
1&
b101011 9
#485000
0&
#490000
b101110 6
b101110 .
b11101111 !
b11101111 +
b11101111 5
b1110001 7
b101110000000000000000000000000 8
1&
b101100 9
#495000
0&
#500000
b101111 6
b101111 .
b101111000000000000000000000000 8
b1110011 7
b11110000 !
b11110000 +
b11110000 5
1&
b101101 9
#505000
0&
#510000
b110000 6
b110000 .
b11110010 !
b11110010 +
b11110010 5
b1110100 7
b110000000000000000000000000000 8
1&
b101110 9
#515000
0&
#520000
b110001 6
b110001 .
b110001000000000000000000000000 8
b1110101 7
b11110011 !
b11110011 +
b11110011 5
1&
b101111 9
#525000
0&
#530000
b110010 6
b110010 .
b11110100 !
b11110100 +
b11110100 5
b1110110 7
b110010000000000000000000000000 8
1&
b110000 9
#535000
0&
#540000
b110011 6
b110011 .
b110011000000000000000000000000 8
b1111000 7
b11110101 !
b11110101 +
b11110101 5
1&
b110001 9
#545000
0&
#550000
b110100 6
b110100 .
b11110111 !
b11110111 +
b11110111 5
b1111001 7
b110100000000000000000000000000 8
1&
b110010 9
#555000
0&
#560000
b110101 6
b110101 .
b110101000000000000000000000000 8
b1111010 7
b11111000 !
b11111000 +
b11111000 5
1&
b110011 9
#565000
0&
#570000
b110110 6
b110110 .
b11111001 !
b11111001 +
b11111001 5
b110110000000000000000000000000 8
1&
b110100 9
#575000
0&
#580000
b110111 6
b110111 .
b110111000000000000000000000000 8
b1111011 7
1&
b110101 9
#585000
0&
#590000
b111000 6
b111000 .
b11111010 !
b11111010 +
b11111010 5
b1111100 7
b111000000000000000000000000000 8
1&
b110110 9
#595000
0&
#600000
b111001 6
b111001 .
b111001000000000000000000000000 8
b1111101 7
b11111011 !
b11111011 +
b11111011 5
1&
b110111 9
#605000
0&
#610000
b111010 6
b111010 .
b11111100 !
b11111100 +
b11111100 5
b111010000000000000000000000000 8
1&
b111000 9
#615000
0&
#620000
b111011 6
b111011 .
b111011000000000000000000000000 8
b1111110 7
1&
b111001 9
#625000
0&
#630000
b111100 6
b111100 .
b11111101 !
b11111101 +
b11111101 5
b111100000000000000000000000000 8
1&
b111010 9
#635000
0&
#640000
b111101 6
b111101 .
b111101000000000000000000000000 8
1&
b111011 9
#645000
0&
#650000
b111110 6
b111110 .
b1111111 7
b111110000000000000000000000000 8
1&
b111100 9
#655000
0&
#660000
b111111 6
b111111 .
b111111000000000000000000000000 8
b11111110 !
b11111110 +
b11111110 5
1&
b111101 9
#665000
0&
#670000
b1 -
b0 .
b1000000000000000000000000000000 8
1&
b111110 9
#675000
0&
#680000
b111110 6
b1 .
b1000001000000000000000000000000 8
1&
b111111 9
#685000
0&
#690000
b111101 6
b10 .
b1000010000000000000000000000000 8
1&
b1000000 9
#695000
0&
#700000
b111100 6
b11 .
b1000011000000000000000000000000 8
1&
b1000001 9
b11111110 (
#705000
0&
#710000
b111011 6
b100 .
b1111110 7
b1000100000000000000000000000000 8
1&
b1000010 9
#715000
0&
#720000
b111010 6
b101 .
b1000101000000000000000000000000 8
b11111101 !
b11111101 +
b11111101 5
1&
b1000011 9
#725000
0&
#730000
b111001 6
b110 .
b1000110000000000000000000000000 8
1&
b1000100 9
#735000
0&
#740000
b111000 6
b111 .
b1000111000000000000000000000000 8
b1111101 7
1&
b1000101 9
#745000
0&
#750000
b110111 6
b1000 .
b11111100 !
b11111100 +
b11111100 5
b1001000000000000000000000000000 8
1&
b1000110 9
#755000
0&
#760000
b110110 6
b1001 .
b1001001000000000000000000000000 8
b1111100 7
1&
b1000111 9
#765000
0&
#770000
b110101 6
b1010 .
b11111011 !
b11111011 +
b11111011 5
b1111011 7
b1001010000000000000000000000000 8
1&
b1001000 9
#775000
0&
#780000
b110100 6
b1011 .
b1001011000000000000000000000000 8
b1111010 7
b11111010 !
b11111010 +
b11111010 5
1&
b1001001 9
#785000
0&
#790000
b110011 6
b1100 .
b11111001 !
b11111001 +
b11111001 5
b1001100000000000000000000000000 8
1&
b1001010 9
#795000
0&
#800000
b110010 6
b1101 .
b1001101000000000000000000000000 8
b1111001 7
1&
b1001011 9
#805000
0&
#810000
b110001 6
b1110 .
b11111000 !
b11111000 +
b11111000 5
b1111000 7
b1001110000000000000000000000000 8
1&
b1001100 9
#815000
0&
#820000
b110000 6
b1111 .
b1001111000000000000000000000000 8
b1110110 7
b11110111 !
b11110111 +
b11110111 5
1&
b1001101 9
#825000
0&
#830000
b101111 6
b10000 .
b11110101 !
b11110101 +
b11110101 5
b1110101 7
b1010000000000000000000000000000 8
1&
b1001110 9
#835000
0&
#840000
b101110 6
b10001 .
b1010001000000000000000000000000 8
b1110100 7
b11110100 !
b11110100 +
b11110100 5
1&
b1001111 9
#845000
0&
#850000
b101101 6
b10010 .
b11110011 !
b11110011 +
b11110011 5
b1110011 7
b1010010000000000000000000000000 8
1&
b1010000 9
#855000
0&
#860000
b101100 6
b10011 .
b1010011000000000000000000000000 8
b1110001 7
b11110010 !
b11110010 +
b11110010 5
1&
b1010001 9
#865000
0&
#870000
b101011 6
b10100 .
b11110000 !
b11110000 +
b11110000 5
b1110000 7
b1010100000000000000000000000000 8
1&
b1010010 9
#875000
0&
#880000
b101010 6
b10101 .
b1010101000000000000000000000000 8
b1101111 7
b11101111 !
b11101111 +
b11101111 5
1&
b1010011 9
#885000
0&
#890000
b101001 6
b10110 .
b11101110 !
b11101110 +
b11101110 5
b1101101 7
b1010110000000000000000000000000 8
1&
b1010100 9
#895000
0&
#900000
b101000 6
b10111 .
b1010111000000000000000000000000 8
b1101011 7
b11101100 !
b11101100 +
b11101100 5
1&
b1010101 9
#905000
0&
#910000
b100111 6
b11000 .
b11101010 !
b11101010 +
b11101010 5
b1101010 7
b1011000000000000000000000000000 8
1&
b1010110 9
#915000
0&
#920000
b100110 6
b11001 .
b1011001000000000000000000000000 8
b1101000 7
b11101001 !
b11101001 +
b11101001 5
1&
b1010111 9
#925000
0&
#930000
b100101 6
b11010 .
b11100111 !
b11100111 +
b11100111 5
b1100110 7
b1011010000000000000000000000000 8
1&
b1011000 9
#935000
0&
#940000
b100100 6
b11011 .
b1011011000000000000000000000000 8
b1100100 7
b11100101 !
b11100101 +
b11100101 5
1&
b1011001 9
#945000
0&
#950000
b100011 6
b11100 .
b11100011 !
b11100011 +
b11100011 5
b1100010 7
b1011100000000000000000000000000 8
1&
b1011010 9
#955000
0&
#960000
b100010 6
b11101 .
b1011101000000000000000000000000 8
b1100000 7
b11100001 !
b11100001 +
b11100001 5
1&
b1011011 9
#965000
0&
#970000
b100001 6
b11110 .
b11011111 !
b11011111 +
b11011111 5
b1011110 7
b1011110000000000000000000000000 8
1&
b1011100 9
#975000
0&
#980000
b100000 6
b11111 .
b1011111000000000000000000000000 8
b1011100 7
b11011101 !
b11011101 +
b11011101 5
1&
b1011101 9
#985000
0&
#990000
b11111 6
b100000 .
b11011011 !
b11011011 +
b11011011 5
b1011010 7
b1100000000000000000000000000000 8
1&
b1011110 9
#995000
0&
#1000000
b11110 6
b100001 .
b1100001000000000000000000000000 8
b1011000 7
b11011001 !
b11011001 +
b11011001 5
1&
b1011111 9
#1005000
0&
#1010000
b11101 6
b100010 .
b11010111 !
b11010111 +
b11010111 5
b1010101 7
b1100010000000000000000000000000 8
1&
b1100000 9
#1015000
0&
#1020000
b11100 6
b100011 .
b1100011000000000000000000000000 8
b1010011 7
b11010100 !
b11010100 +
b11010100 5
1&
b1100001 9
#1025000
0&
#1030000
b11011 6
b100100 .
b11010010 !
b11010010 +
b11010010 5
b1010001 7
b1100100000000000000000000000000 8
1&
b1100010 9
#1035000
0&
#1040000
b11010 6
b100101 .
b1100101000000000000000000000000 8
b1001110 7
b11010000 !
b11010000 +
b11010000 5
1&
b1100011 9
#1045000
0&
#1050000
b11001 6
b100110 .
b11001101 !
b11001101 +
b11001101 5
b1001100 7
b1100110000000000000000000000000 8
1&
b1100100 9
#1055000
0&
#1060000
b11000 6
b100111 .
b1100111000000000000000000000000 8
b1001001 7
b11001011 !
b11001011 +
b11001011 5
1&
b1100101 9
#1065000
0&
#1070000
b10111 6
b101000 .
b11001000 !
b11001000 +
b11001000 5
b1000111 7
b1101000000000000000000000000000 8
1&
b1100110 9
#1075000
0&
#1080000
b10110 6
b101001 .
b1101001000000000000000000000000 8
b1000100 7
b11000110 !
b11000110 +
b11000110 5
1&
b1100111 9
#1085000
0&
#1090000
b10101 6
b101010 .
b11000011 !
b11000011 +
b11000011 5
b1000001 7
b1101010000000000000000000000000 8
1&
b1101000 9
#1095000
0&
#1100000
b10100 6
b101011 .
b1101011000000000000000000000000 8
b111111 7
b11000000 !
b11000000 +
b11000000 5
1&
b1101001 9
#1105000
0&
#1110000
b10011 6
b101100 .
b10111110 !
b10111110 +
b10111110 5
b111100 7
b1101100000000000000000000000000 8
1&
b1101010 9
#1115000
0&
#1120000
b10010 6
b101101 .
b1101101000000000000000000000000 8
b111001 7
b10111011 !
b10111011 +
b10111011 5
1&
b1101011 9
#1125000
0&
#1130000
b10001 6
b101110 .
b10111000 !
b10111000 +
b10111000 5
b110110 7
b1101110000000000000000000000000 8
1&
b1101100 9
#1135000
0&
#1140000
b10000 6
b101111 .
b1101111000000000000000000000000 8
b110011 7
b10110101 !
b10110101 +
b10110101 5
1&
b1101101 9
#1145000
0&
#1150000
b1111 6
b110000 .
b10110010 !
b10110010 +
b10110010 5
b110001 7
b1110000000000000000000000000000 8
1&
b1101110 9
#1155000
0&
#1160000
b1110 6
b110001 .
b1110001000000000000000000000000 8
b101110 7
b10110000 !
b10110000 +
b10110000 5
1&
b1101111 9
#1165000
0&
#1170000
b1101 6
b110010 .
b10101101 !
b10101101 +
b10101101 5
b101011 7
b1110010000000000000000000000000 8
1&
b1110000 9
#1175000
0&
#1180000
b1100 6
b110011 .
b1110011000000000000000000000000 8
b101000 7
b10101010 !
b10101010 +
b10101010 5
1&
b1110001 9
#1185000
0&
#1190000
b1011 6
b110100 .
b10100111 !
b10100111 +
b10100111 5
b100101 7
b1110100000000000000000000000000 8
1&
b1110010 9
#1195000
0&
#1200000
b1010 6
b110101 .
b1110101000000000000000000000000 8
b100010 7
b10100100 !
b10100100 +
b10100100 5
1&
b1110011 9
#1205000
0&
#1210000
b1001 6
b110110 .
b10100001 !
b10100001 +
b10100001 5
b11111 7
b1110110000000000000000000000000 8
1&
b1110100 9
#1215000
0&
#1220000
b1000 6
b110111 .
b1110111000000000000000000000000 8
b11100 7
b10011110 !
b10011110 +
b10011110 5
1&
b1110101 9
#1225000
0&
#1230000
b111 6
b111000 .
b10011011 !
b10011011 +
b10011011 5
b11001 7
b1111000000000000000000000000000 8
1&
b1110110 9
#1235000
0&
#1240000
b110 6
b111001 .
b1111001000000000000000000000000 8
b10110 7
b10011000 !
b10011000 +
b10011000 5
1&
b1110111 9
#1245000
0&
#1250000
b101 6
b111010 .
b10010101 !
b10010101 +
b10010101 5
b10011 7
b1111010000000000000000000000000 8
1&
b1111000 9
#1255000
0&
#1260000
b100 6
b111011 .
b1111011000000000000000000000000 8
b10000 7
b10010010 !
b10010010 +
b10010010 5
1&
b1111001 9
#1265000
0&
#1270000
b11 6
b111100 .
b10001111 !
b10001111 +
b10001111 5
b1100 7
b1111100000000000000000000000000 8
1&
b1111010 9
#1275000
0&
#1280000
b10 6
b111101 .
b1111101000000000000000000000000 8
b1001 7
b10001011 !
b10001011 +
b10001011 5
1&
b1111011 9
#1285000
0&
#1290000
b1 6
b111110 .
b10001000 !
b10001000 +
b10001000 5
b110 7
b1111110000000000000000000000000 8
1&
b1111100 9
#1295000
0&
#1300000
b0 6
b111111 .
b1111111000000000000000000000000 8
b11 7
b10000101 !
b10000101 +
b10000101 5
1&
b1111101 9
#1305000
0&
#1310000
b10 -
b0 .
b10000010 !
b10000010 +
b10000010 5
b0 7
b10000000000000000000000000000000 8
1&
b1111110 9
#1315000
0&
#1320000
b1 6
b1 .
b10000001000000000000000000000000 8
b1111111 !
b1111111 +
b1111111 5
1&
b1111111 9
#1325000
0&
#1330000
b10 6
b10 .
b11 7
b10000010000000000000000000000000 8
1&
b10000000 9
#1335000
0&
#1340000
b11 6
b11 .
b10000011000000000000000000000000 8
b110 7
b1111100 !
b1111100 +
b1111100 5
1&
b10000001 9
b1111111 (
#1345000
0&
#1350000
b100 6
b100 .
b1111001 !
b1111001 +
b1111001 5
b1001 7
b10000100000000000000000000000000 8
1&
b10000010 9
#1355000
0&
#1360000
b101 6
b101 .
b10000101000000000000000000000000 8
b1100 7
b1110110 !
b1110110 +
b1110110 5
1&
b10000011 9
#1365000
0&
#1370000
b110 6
b110 .
b1110011 !
b1110011 +
b1110011 5
b10000 7
b10000110000000000000000000000000 8
1&
b10000100 9
#1375000
0&
#1380000
b111 6
b111 .
b10000111000000000000000000000000 8
b10011 7
b1101111 !
b1101111 +
b1101111 5
1&
b10000101 9
#1385000
0&
#1390000
b1000 6
b1000 .
b1101100 !
b1101100 +
b1101100 5
b10110 7
b10001000000000000000000000000000 8
1&
b10000110 9
#1395000
0&
#1400000
b1001 6
b1001 .
b10001001000000000000000000000000 8
b11001 7
b1101001 !
b1101001 +
b1101001 5
1&
b10000111 9
#1405000
0&
#1410000
b1010 6
b1010 .
b1100110 !
b1100110 +
b1100110 5
b11100 7
b10001010000000000000000000000000 8
1&
b10001000 9
#1415000
0&
#1420000
b1011 6
b1011 .
b10001011000000000000000000000000 8
b11111 7
b1100011 !
b1100011 +
b1100011 5
1&
b10001001 9
#1425000
0&
#1430000
b1100 6
b1100 .
b1100000 !
b1100000 +
b1100000 5
b100010 7
b10001100000000000000000000000000 8
1&
b10001010 9
#1435000
0&
#1440000
b1101 6
b1101 .
b10001101000000000000000000000000 8
b100101 7
b1011101 !
b1011101 +
b1011101 5
1&
b10001011 9
#1445000
0&
#1450000
b1110 6
b1110 .
b1011010 !
b1011010 +
b1011010 5
b101000 7
b10001110000000000000000000000000 8
1&
b10001100 9
#1455000
0&
#1460000
b1111 6
b1111 .
b10001111000000000000000000000000 8
b101011 7
b1010111 !
b1010111 +
b1010111 5
1&
b10001101 9
#1465000
0&
#1470000
b10000 6
b10000 .
b1010100 !
b1010100 +
b1010100 5
b101110 7
b10010000000000000000000000000000 8
1&
b10001110 9
#1475000
0&
#1480000
b10001 6
b10001 .
b10010001000000000000000000000000 8
b110001 7
b1010001 !
b1010001 +
b1010001 5
1&
b10001111 9
#1485000
0&
#1490000
b10010 6
b10010 .
b1001110 !
b1001110 +
b1001110 5
b110011 7
b10010010000000000000000000000000 8
1&
b10010000 9
#1495000
0&
#1500000
b10011 6
b10011 .
b10010011000000000000000000000000 8
b110110 7
b1001100 !
b1001100 +
b1001100 5
1&
b10010001 9
#1505000
0&
#1510000
b10100 6
b10100 .
b1001001 !
b1001001 +
b1001001 5
b111001 7
b10010100000000000000000000000000 8
1&
b10010010 9
#1515000
0&
#1520000
b10101 6
b10101 .
b10010101000000000000000000000000 8
b111100 7
b1000110 !
b1000110 +
b1000110 5
1&
b10010011 9
#1525000
0&
#1530000
b10110 6
b10110 .
b1000011 !
b1000011 +
b1000011 5
b111111 7
b10010110000000000000000000000000 8
1&
b10010100 9
#1535000
0&
#1540000
b10111 6
b10111 .
b10010111000000000000000000000000 8
b1000001 7
b1000000 !
b1000000 +
b1000000 5
1&
b10010101 9
#1545000
0&
#1550000
b11000 6
b11000 .
b111110 !
b111110 +
b111110 5
b1000100 7
b10011000000000000000000000000000 8
1&
b10010110 9
#1555000
0&
#1560000
b11001 6
b11001 .
b10011001000000000000000000000000 8
b1000111 7
b111011 !
b111011 +
b111011 5
1&
b10010111 9
#1565000
0&
#1570000
b11010 6
b11010 .
b111000 !
b111000 +
b111000 5
b1001001 7
b10011010000000000000000000000000 8
1&
b10011000 9
#1575000
0&
#1580000
b11011 6
b11011 .
b10011011000000000000000000000000 8
b1001100 7
b110110 !
b110110 +
b110110 5
1&
b10011001 9
#1585000
0&
#1590000
b11100 6
b11100 .
b110011 !
b110011 +
b110011 5
b1001110 7
b10011100000000000000000000000000 8
1&
b10011010 9
#1595000
0&
